vega/__init__.py
vega/_frontend.py
vega/altair.py
vega/base.py
vega/static/extension.js
vega/static/extension.js.map
vega/static/index.js
vega/static/index.js.LICENSE.txt
vega/static/index.js.map
vega/static/labplugin.js
vega/static/labplugin.js.LICENSE.txt
vega/static/labplugin.js.map
vega/static/vega.js
vega/tests/__init__.py
vega/tests/test_entrypoint.py
vega/tests/test_outputs.py
vega/tests/test_utils.py
vega/utils.py
vega/vega.py
vega/vegalite.py
vega/widget.py
vega-4.1.0.dist-info/LICENSE
vega-4.1.0.dist-info/METADATA
vega-4.1.0.dist-info/WHEEL
vega-4.1.0.dist-info/entry_points.txt
vega-4.1.0.dist-info/RECORD
