Metadata-Version: 2.1
Name: vega
Version: 4.1.0
Summary: A Jupyter widget for Vega 5 and Vega-Lite 4
Home-page: https://github.com/vega/ipyvega
License: BSD 3-clause
Author: Dominik Moritz
Author-email: domoritz@gmail.com
Requires-Python: >=3.8.0
Classifier: Development Status :: 5 - Production/Stable
Classifier: Environment :: Console
Classifier: Intended Audience :: Science/Research
Classifier: License :: OSI Approved :: BSD License
Classifier: License :: Other/Proprietary License
Classifier: Natural Language :: English
Classifier: Programming Language :: Python :: 3
Classifier: Programming Language :: Python :: 3.8
Classifier: Programming Language :: Python :: 3.9
Classifier: Programming Language :: Python :: 3.10
Classifier: Programming Language :: Python :: 3.11
Classifier: Programming Language :: Python :: 3.12
Provides-Extra: jupyterlab
Provides-Extra: widget
Requires-Dist: ipytablewidgets (>=0.3.0,<0.4.0)
Requires-Dist: jupyter (>=1.0.0,<2.0.0)
Requires-Dist: pandas (>=1.5.0)
Project-URL: Repository, https://github.com/vega/ipyvega
